{
  "version": "21.0.0",
  "files": {
    "ef600f80a6e07d0b4d5c58b473d957a4d6e9508b95653adc8579629ac9643a31": {
      "source": {
        "path": "ProjectAtallaWsStack.template.json",
        "packaging": "file"
      },
      "destinations": {
        "current_account-current_region": {
          "bucketName": "cdk-hnb659fds-assets-${AWS::AccountId}-${AWS::Region}",
          "objectKey": "ef600f80a6e07d0b4d5c58b473d957a4d6e9508b95653adc8579629ac9643a31.json",
          "assumeRoleArn": "arn:${AWS::Partition}:iam::${AWS::AccountId}:role/cdk-hnb659fds-file-publishing-role-${AWS::AccountId}-${AWS::Region}"
        }
      }
    }
  },
  "dockerImages": {}
}