{
  "version": "21.0.0",
  "files": {
    "fe5b90115947c0bd569320b31ab77e709322784bb7b5c4b72e5c060a2b66eb1d": {
      "source": {
        "path": "ProjectAtallaKmsStack.template.json",
        "packaging": "file"
      },
      "destinations": {
        "current_account-current_region": {
          "bucketName": "cdk-hnb659fds-assets-${AWS::AccountId}-${AWS::Region}",
          "objectKey": "fe5b90115947c0bd569320b31ab77e709322784bb7b5c4b72e5c060a2b66eb1d.json",
          "assumeRoleArn": "arn:${AWS::Partition}:iam::${AWS::AccountId}:role/cdk-hnb659fds-file-publishing-role-${AWS::AccountId}-${AWS::Region}"
        }
      }
    }
  },
  "dockerImages": {}
}